calculator/server.py
calculator_for_all_task-0.1.4.dist-info/METADATA
calculator_for_all_task-0.1.4.dist-info/WHEEL
calculator_for_all_task-0.1.4.dist-info/entry_points.txt
calculator_for_all_task-0.1.4.dist-info/top_level.txt
calculator_for_all_task-0.1.4.dist-info/RECORD
