Metadata-Version: 2.4
Name: calculator-for-all-task
Version: 0.1.4
Summary: A calculator MCP server with basic and advanced math operations
Requires-Python: >=3.10
Requires-Dist: mcp[cli]>=1.0.0
